Workbook

Sheet Supuestos
A1: Venta de huevos en Lima: supuestos
A2: Edita solo las celdas amarillas (texto azul). Todo lo demás se recalcula solo.
A3: Supuesto | B3: Valor | C3: Nota
A4: Precio de compra por kg (granja o mayorista) | B4: 5.9 | C4: Estimado. Confírmalo con granjas de Huaral, Chancay o Lurín y con el MIDAGRI (SISAP).
A5: Precio de venta promedio por kg (canal mixto) | B5: 7.2 | C5: Mitad a hogares (~S/ 7.80) y mitad a bodegas (~S/ 6.70).
A6: Huevos rotos o perdidos (% de la compra) | B6: 0.02 | C6: Entre 2% y 3% es lo habitual.
A7: Bolsas y empaque por kg | B7: 0.08 | C7: Estimado.
A8: Combustible por kg | B8: 0.1 | C8: Estimado. Sube si entregas a muchos hogares lejanos.
A9: Peso de una bandeja de 30 huevos (kg) | B9: 1.85 | C9: Huevo mediano o grande.
A10: Huevos por bandeja | B10: 30
A11: Bandejas por jaba | B11: 12 | C11: Una jaba tiene 360 huevos.
A12: Días trabajados al mes | B12: 26 | C12: De lunes a sábado.
A13: Días de stock como capital de trabajo | B13: 2 | C13: Dinero que necesitas tener para comprar mercadería por adelantado.
A15: Ganancia limpia por kg (canal mixto) | B15: =B5-B4-B4*B6-B7-B8 | C15: Precio de venta − compra − huevos rotos − empaque − combustible
A17: Gastos fijos por día según el tamaño del negocio
A18: Nivel | B18: Gasto fijo al día | C18: Se aplica desde una ganancia diaria de
A19: Tú solo, con moto o mototaxi (combustible base y celular) | B19: 30 | C19: 0
A20: Moto carguera o furgoneta y 1 ayudante | B20: 100 | C20: 201
A21: Distribuidora: camioneta, 2 ayudantes y almacén | B21: 200 | C21: 501
A23: Leyenda: celdas amarillas con texto azul = datos que puedes cambiar · texto negro = fórmulas · texto verde = valores tomados de esta hoja.
A24: Todas las cifras son estimaciones de referencia (octubre de 2026). Antes de invertir, verifica los precios reales.

Sheet Metas diarias
A1: Cuánto vender para ganar S/ 100 a S/ 1,000 al día
A2: Puedes cambiar las metas de la columna A (amarillas). Los precios y costos se cambian en la hoja Supuestos.
A3: Ganancia que quieres al día | B3: Gasto fijo al día | C3: Kg al día | D3: Bandejas al día | E3: Huevos al día | F3: Jabas al día | G3: Ventas al día | H3: Compra al día | I3: Capital de trabajo necesario | J3: Ganancia al mes
A4: 100 | B4: =INDEX(Supuestos!$B$19:$B$21,MATCH(A4,Supuestos!$C$19:$C$21,1)) | C4: =IF(Supuestos!$B$15<=0,0,(A4+B4)/Supuestos!$B$15) | D4: =C4/Supuestos!$B$9 | E4: =D4*Supuestos!$B$10 | F4: =D4/Supuestos!$B$11 | G4: =C4*Supuestos!$B$5 | H4: =C4*Supuestos!$B$4 | I4: =H4*Supuestos!$B$13 | J4: =A4*Supuestos!$B$12
A5: 200 | B5: =INDEX(Supuestos!$B$19:$B$21,MATCH(A5,Supuestos!$C$19:$C$21,1)) | C5: =IF(Supuestos!$B$15<=0,0,(A5+B5)/Supuestos!$B$15) | D5: =C5/Supuestos!$B$9 | E5: =D5*Supuestos!$B$10 | F5: =D5/Supuestos!$B$11 | G5: =C5*Supuestos!$B$5 | H5: =C5*Supuestos!$B$4 | I5: =H5*Supuestos!$B$13 | J5: =A5*Supuestos!$B$12
A6: 300 | B6: =INDEX(Supuestos!$B$19:$B$21,MATCH(A6,Supuestos!$C$19:$C$21,1)) | C6: =IF(Supuestos!$B$15<=0,0,(A6+B6)/Supuestos!$B$15) | D6: =C6/Supuestos!$B$9 | E6: =D6*Supuestos!$B$10 | F6: =D6/Supuestos!$B$11 | G6: =C6*Supuestos!$B$5 | H6: =C6*Supuestos!$B$4 | I6: =H6*Supuestos!$B$13 | J6: =A6*Supuestos!$B$12
A7: 400 | B7: =INDEX(Supuestos!$B$19:$B$21,MATCH(A7,Supuestos!$C$19:$C$21,1)) | C7: =IF(Supuestos!$B$15<=0,0,(A7+B7)/Supuestos!$B$15) | D7: =C7/Supuestos!$B$9 | E7: =D7*Supuestos!$B$10 | F7: =D7/Supuestos!$B$11 | G7: =C7*Supuestos!$B$5 | H7: =C7*Supuestos!$B$4 | I7: =H7*Supuestos!$B$13 | J7: =A7*Supuestos!$B$12
A8: 500 | B8: =INDEX(Supuestos!$B$19:$B$21,MATCH(A8,Supuestos!$C$19:$C$21,1)) | C8: =IF(Supuestos!$B$15<=0,0,(A8+B8)/Supuestos!$B$15) | D8: =C8/Supuestos!$B$9 | E8: =D8*Supuestos!$B$10 | F8: =D8/Supuestos!$B$11 | G8: =C8*Supuestos!$B$5 | H8: =C8*Supuestos!$B$4 | I8: =H8*Supuestos!$B$13 | J8: =A8*Supuestos!$B$12
A9: 600 | B9: =INDEX(Supuestos!$B$19:$B$21,MATCH(A9,Supuestos!$C$19:$C$21,1)) | C9: =IF(Supuestos!$B$15<=0,0,(A9+B9)/Supuestos!$B$15) | D9: =C9/Supuestos!$B$9 | E9: =D9*Supuestos!$B$10 | F9: =D9/Supuestos!$B$11 | G9: =C9*Supuestos!$B$5 | H9: =C9*Supuestos!$B$4 | I9: =H9*Supuestos!$B$13 | J9: =A9*Supuestos!$B$12
A10: 700 | B10: =INDEX(Supuestos!$B$19:$B$21,MATCH(A10,Supuestos!$C$19:$C$21,1)) | C10: =IF(Supuestos!$B$15<=0,0,(A10+B10)/Supuestos!$B$15) | D10: =C10/Supuestos!$B$9 | E10: =D10*Supuestos!$B$10 | F10: =D10/Supuestos!$B$11 | G10: =C10*Supuestos!$B$5 | H10: =C10*Supuestos!$B$4 | I10: =H10*Supuestos!$B$13 | J10: =A10*Supuestos!$B$12
A11: 800 | B11: =INDEX(Supuestos!$B$19:$B$21,MATCH(A11,Supuestos!$C$19:$C$21,1)) | C11: =IF(Supuestos!$B$15<=0,0,(A11+B11)/Supuestos!$B$15) | D11: =C11/Supuestos!$B$9 | E11: =D11*Supuestos!$B$10 | F11: =D11/Supuestos!$B$11 | G11: =C11*Supuestos!$B$5 | H11: =C11*Supuestos!$B$4 | I11: =H11*Supuestos!$B$13 | J11: =A11*Supuestos!$B$12
A12: 900 | B12: =INDEX(Supuestos!$B$19:$B$21,MATCH(A12,Supuestos!$C$19:$C$21,1)) | C12: =IF(Supuestos!$B$15<=0,0,(A12+B12)/Supuestos!$B$15) | D12: =C12/Supuestos!$B$9 | E12: =D12*Supuestos!$B$10 | F12: =D12/Supuestos!$B$11 | G12: =C12*Supuestos!$B$5 | H12: =C12*Supuestos!$B$4 | I12: =H12*Supuestos!$B$13 | J12: =A12*Supuestos!$B$12
A13: 1000 | B13: =INDEX(Supuestos!$B$19:$B$21,MATCH(A13,Supuestos!$C$19:$C$21,1)) | C13: =IF(Supuestos!$B$15<=0,0,(A13+B13)/Supuestos!$B$15) | D13: =C13/Supuestos!$B$9 | E13: =D13*Supuestos!$B$10 | F13: =D13/Supuestos!$B$11 | G13: =C13*Supuestos!$B$5 | H13: =C13*Supuestos!$B$4 | I13: =H13*Supuestos!$B$13 | J13: =A13*Supuestos!$B$12
A15: Cálculo: kg al día = (ganancia que quieres + gasto fijo) ÷ ganancia limpia por kg. El gasto fijo depende del nivel del negocio (hoja Supuestos).

Sheet Por canal de venta
A1: Bandejas al día según a quién le vendes
A2: Cambia los precios de venta de cada canal (amarillos). Los costos se toman de la hoja Supuestos.
A4: Concepto | B4: Solo bodegas | C4: Mixto | D4: Solo hogares con delivery
A5: Precio de venta por kg | B5: 6.7 | C5: =Supuestos!B5 | D5: 7.8
A6: Ganancia limpia por kg | B6: =B5-Supuestos!$B$4-Supuestos!$B$4*Supuestos!$B$6-Supuestos!$B$7-Supuestos!$B$8 | C6: =C5-Supuestos!$B$4-Supuestos!$B$4*Supuestos!$B$6-Supuestos!$B$7-Supuestos!$B$8 | D6: =D5-Supuestos!$B$4-Supuestos!$B$4*Supuestos!$B$6-Supuestos!$B$7-Supuestos!$B$8
A8: Ganancia que quieres al día | B8: Bandejas al día: solo bodegas | C8: Bandejas al día: mixto | D8: Bandejas al día: solo hogares
A9: ='Metas diarias'!A4 | B9: =IF(B$6<=0,"Pierdes dinero",('Metas diarias'!$A4+'Metas diarias'!$B4)/B$6/Supuestos!$B$9) | C9: =IF(C$6<=0,"Pierdes dinero",('Metas diarias'!$A4+'Metas diarias'!$B4)/C$6/Supuestos!$B$9) | D9: =IF(D$6<=0,"Pierdes dinero",('Metas diarias'!$A4+'Metas diarias'!$B4)/D$6/Supuestos!$B$9)
A10: ='Metas diarias'!A5 | B10: =IF(B$6<=0,"Pierdes dinero",('Metas diarias'!$A5+'Metas diarias'!$B5)/B$6/Supuestos!$B$9) | C10: =IF(C$6<=0,"Pierdes dinero",('Metas diarias'!$A5+'Metas diarias'!$B5)/C$6/Supuestos!$B$9) | D10: =IF(D$6<=0,"Pierdes dinero",('Metas diarias'!$A5+'Metas diarias'!$B5)/D$6/Supuestos!$B$9)
A11: ='Metas diarias'!A6 | B11: =IF(B$6<=0,"Pierdes dinero",('Metas diarias'!$A6+'Metas diarias'!$B6)/B$6/Supuestos!$B$9) | C11: =IF(C$6<=0,"Pierdes dinero",('Metas diarias'!$A6+'Metas diarias'!$B6)/C$6/Supuestos!$B$9) | D11: =IF(D$6<=0,"Pierdes dinero",('Metas diarias'!$A6+'Metas diarias'!$B6)/D$6/Supuestos!$B$9)
A12: ='Metas diarias'!A7 | B12: =IF(B$6<=0,"Pierdes dinero",('Metas diarias'!$A7+'Metas diarias'!$B7)/B$6/Supuestos!$B$9) | C12: =IF(C$6<=0,"Pierdes dinero",('Metas diarias'!$A7+'Metas diarias'!$B7)/C$6/Supuestos!$B$9) | D12: =IF(D$6<=0,"Pierdes dinero",('Metas diarias'!$A7+'Metas diarias'!$B7)/D$6/Supuestos!$B$9)
A13: ='Metas diarias'!A8 | B13: =IF(B$6<=0,"Pierdes dinero",('Metas diarias'!$A8+'Metas diarias'!$B8)/B$6/Supuestos!$B$9) | C13: =IF(C$6<=0,"Pierdes dinero",('Metas diarias'!$A8+'Metas diarias'!$B8)/C$6/Supuestos!$B$9) | D13: =IF(D$6<=0,"Pierdes dinero",('Metas diarias'!$A8+'Metas diarias'!$B8)/D$6/Supuestos!$B$9)
A14: ='Metas diarias'!A9 | B14: =IF(B$6<=0,"Pierdes dinero",('Metas diarias'!$A9+'Metas diarias'!$B9)/B$6/Supuestos!$B$9) | C14: =IF(C$6<=0,"Pierdes dinero",('Metas diarias'!$A9+'Metas diarias'!$B9)/C$6/Supuestos!$B$9) | D14: =IF(D$6<=0,"Pierdes dinero",('Metas diarias'!$A9+'Metas diarias'!$B9)/D$6/Supuestos!$B$9)
A15: ='Metas diarias'!A10 | B15: =IF(B$6<=0,"Pierdes dinero",('Metas diarias'!$A10+'Metas diarias'!$B10)/B$6/Supuestos!$B$9) | C15: =IF(C$6<=0,"Pierdes dinero",('Metas diarias'!$A10+'Metas diarias'!$B10)/C$6/Supuestos!$B$9) | D15: =IF(D$6<=0,"Pierdes dinero",('Metas diarias'!$A10+'Metas diarias'!$B10)/D$6/Supuestos!$B$9)
A16: ='Metas diarias'!A11 | B16: =IF(B$6<=0,"Pierdes dinero",('Metas diarias'!$A11+'Metas diarias'!$B11)/B$6/Supuestos!$B$9) | C16: =IF(C$6<=0,"Pierdes dinero",('Metas diarias'!$A11+'Metas diarias'!$B11)/C$6/Supuestos!$B$9) | D16: =IF(D$6<=0,"Pierdes dinero",('Metas diarias'!$A11+'Metas diarias'!$B11)/D$6/Supuestos!$B$9)
A17: ='Metas diarias'!A12 | B17: =IF(B$6<=0,"Pierdes dinero",('Metas diarias'!$A12+'Metas diarias'!$B12)/B$6/Supuestos!$B$9) | C17: =IF(C$6<=0,"Pierdes dinero",('Metas diarias'!$A12+'Metas diarias'!$B12)/C$6/Supuestos!$B$9) | D17: =IF(D$6<=0,"Pierdes dinero",('Metas diarias'!$A12+'Metas diarias'!$B12)/D$6/Supuestos!$B$9)
A18: ='Metas diarias'!A13 | B18: =IF(B$6<=0,"Pierdes dinero",('Metas diarias'!$A13+'Metas diarias'!$B13)/B$6/Supuestos!$B$9) | C18: =IF(C$6<=0,"Pierdes dinero",('Metas diarias'!$A13+'Metas diarias'!$B13)/C$6/Supuestos!$B$9) | D18: =IF(D$6<=0,"Pierdes dinero",('Metas diarias'!$A13+'Metas diarias'!$B13)/D$6/Supuestos!$B$9)
A20: Incluye el gasto fijo de cada nivel. Vender a hogares deja más ganancia por bandeja, pero cada entrega es pequeña y toma más tiempo.
