Workbook

Sheet Supuestos
A1: Saneamiento ambiental en Lima: supuestos
A2: Edita solo las celdas amarillas (texto azul). Todo lo demás se recalcula solo. Precios = lo que paga el cliente (con IGV).
A4: Servicio | B4: Precio cobrado (con IGV) | C4: Insumos | D4: Mano de obra (técnico) | E4: Movilidad | F4: % de los servicios | G4: Precio sin IGV | H4: Costo variable | I4: Contribución por servicio | J4: Nota
A5: Fumigación + desinfección local pequeño (≤100 m²: bodega, tienda, oficina) | B5: 150 | C5: 20 | D5: 40 | E5: 15 | F5: 0.45 | G5: =B5/(1+$B$14) | H5: =C5+D5+E5 | I5: =G5-H5 | J5: Mercado en Lima: desde S/ 100–135.
A6: Fumigación restaurante / pollería (150–250 m²) | B6: 380 | C6: 45 | D6: 70 | E6: 15 | F6: 0.2 | G6: =B6/(1+$B$14) | H6: =C6+D6+E6 | I6: =G6-H6 | J6: Mercado: desde S/ 400.
A7: Limpieza y desinfección cisterna + tanque elevado (edificio) | B7: 550 | C7: 35 | D7: 160 | E7: 30 | F7: 0.15 | G7: =B7/(1+$B$14) | H7: =C7+D7+E7 | I7: =G7-H7 | J7: Mercado: S/ 350–800 según volumen. 2 técnicos.
A8: Contrato mensual de control de plagas (restaurante) | B8: 200 | C8: 35 | D8: 40 | E8: 10 | F8: 0.15 | G8: =B8/(1+$B$14) | H8: =C8+D8+E8 | I8: =G8-H8 | J8: Visita mensual; el cliente renueva solo.
A9: Fumigación de vivienda | B9: 180 | C9: 25 | D9: 40 | E9: 15 | F9: 0.05 | G9: =B9/(1+$B$14) | H9: =C9+D9+E9 | I9: =G9-H9 | J9: Sube en verano (dengue, cucarachas).
A10: Promedio ponderado por servicio | B10: =SUMPRODUCT(B5:B9,$F$5:$F$9) | F10: =SUM(F5:F9) | G10: =SUMPRODUCT(G5:G9,$F$5:$F$9) | H10: =SUMPRODUCT(H5:H9,$F$5:$F$9) | I10: =SUMPRODUCT(I5:I9,$F$5:$F$9) | J10: La columna F debe sumar 100%.
A13: Impuestos
A14: IGV | B14: 0.18 | C14: Se descuenta del precio cobrado (conservador: no resta el IGV de tus compras).
A15: Impuesto a la renta (Régimen MYPE: 10% hasta 15 UIT de utilidad) | B15: 0.1
A17: Gastos fijos al mes
A18: Almacén pequeño / oficina (exigido para guardar productos) | B18: 800 | C18: Depósitos en Lima Norte/Este desde S/ 250–1,800.
A19: Contador | B19: 250
A20: Marketing digital (Google Maps, Meta, Google Ads) | B20: 800 | C20: La clave del negocio. No recortar.
A21: Celular, internet, software de agenda y facturación | B21: 120
A22: Cuota CIP y certificado de habilidad | B22: 40 | C22: Tú como director técnico.
A23: SCTR y seguros de los técnicos | B23: 100 | C23: Obligatorio para actividad de riesgo.
A24: Otros (uniformes, mantenimiento de equipos, imprevistos) | B24: 200
A25: Total gastos fijos al mes | B25: =SUM(B18:B24)
A26: Servicios al mes para no perder dinero (punto de equilibrio) | B26: =ROUNDUP(B25/I10,0)
A28: Leyenda: celdas amarillas con texto azul = datos que puedes cambiar · texto negro = fórmulas · texto verde = valores tomados de otra hoja.
A29: Cifras de referencia (octubre de 2026). Antes de invertir, confirma precios con 10 llamadas a competidores y 50 negocios de tu zona.

Sheet Inversión inicial
A1: Inversión inicial estimada
A2: Cambia los montos amarillos. Si ya estás colegiado en el CIP, pon 0 en esa fila.
A4: Concepto | B4: Monto | C4: Nota
A5: Colegiatura CIP Lima (si aún no la tienes) | B5: 1432 | C5: Requisito para ser director técnico. Ingeniería industrial califica (D.S. 022-2001-SA, art. 14).
A6: Constitución de empresa (SAC/EIRL) y licencia de funcionamiento | B6: 900 | C6: Constitución vía SID-SUNARP + licencia municipal del almacén.
A7: Trámite de autorización ante la DIRIS de tu zona | B7: 400 | C7: Verificar tasa exacta en el TUPA de la DIRIS (Centro/Norte/Sur/Este).
A8: 2 fumigadoras manuales de presión 20 L | B8: 700
A9: Nebulizadora ULV eléctrica | B9: 1200 | C9: Puedes postergarla al mes 2–3.
A10: Equipo para cisternas: bomba sumergible, cepillos, escalera, linterna | B10: 700
A11: Equipo de protección personal (respiradores, overoles, lentes, guantes, botas) | B11: 400
A12: Insumos iniciales con registro DIGESA (insecticidas, cebos gel, rodenticidas, desinfectantes, cloro) | B12: 800
A13: Marca, uniformes, stickers de certificado, volantes | B13: 400
A14: Marketing de lanzamiento (primer mes de anuncios) | B14: 600
A15: Capital de trabajo (1 mes de gastos fijos parciales) | B15: 1000
A16: Total inversión inicial | B16: =SUM(B5:B15)

Sheet Proyección 12 meses
A1: Proyección a 12 meses
A2: Escenario: % del volumen planeado que realmente logras | F2: 1 | G2: Prueba con 60% para ver el escenario conservador.
A4: Mes | B4: Servicios planeados | C4: Servicios logrados | D4: Ventas (con IGV) | E4: Ventas sin IGV | F4: Costo variable | G4: Contribución | H4: Gastos fijos | I4: Utilidad antes de renta | J4: Impuesto a la renta | K4: Utilidad neta (tu ingreso) | L4: Caja acumulada (descontando inversión) | M4: Mes con caja positiva
A5: 1 | B5: 15 | C5: =ROUND(B5*$F$2,0) | D5: =C5*Supuestos!$B$10 | E5: =C5*Supuestos!$G$10 | F5: =C5*Supuestos!$H$10 | G5: =E5-F5 | H5: =Supuestos!$B$25 | I5: =G5-H5 | J5: =MAX(0,I5)*Supuestos!$B$15 | K5: =I5-J5 | L5: =-'Inversión inicial'!$B$16+K5 | M5: =IF(L5>=0,A5,"")
A6: 2 | B6: 25 | C6: =ROUND(B6*$F$2,0) | D6: =C6*Supuestos!$B$10 | E6: =C6*Supuestos!$G$10 | F6: =C6*Supuestos!$H$10 | G6: =E6-F6 | H6: =Supuestos!$B$25 | I6: =G6-H6 | J6: =MAX(0,I6)*Supuestos!$B$15 | K6: =I6-J6 | L6: =L5+K6 | M6: =IF(L6>=0,A6,"")
A7: 3 | B7: 35 | C7: =ROUND(B7*$F$2,0) | D7: =C7*Supuestos!$B$10 | E7: =C7*Supuestos!$G$10 | F7: =C7*Supuestos!$H$10 | G7: =E7-F7 | H7: =Supuestos!$B$25 | I7: =G7-H7 | J7: =MAX(0,I7)*Supuestos!$B$15 | K7: =I7-J7 | L7: =L6+K7 | M7: =IF(L7>=0,A7,"")
A8: 4 | B8: 45 | C8: =ROUND(B8*$F$2,0) | D8: =C8*Supuestos!$B$10 | E8: =C8*Supuestos!$G$10 | F8: =C8*Supuestos!$H$10 | G8: =E8-F8 | H8: =Supuestos!$B$25 | I8: =G8-H8 | J8: =MAX(0,I8)*Supuestos!$B$15 | K8: =I8-J8 | L8: =L7+K8 | M8: =IF(L8>=0,A8,"")
A9: 5 | B9: 55 | C9: =ROUND(B9*$F$2,0) | D9: =C9*Supuestos!$B$10 | E9: =C9*Supuestos!$G$10 | F9: =C9*Supuestos!$H$10 | G9: =E9-F9 | H9: =Supuestos!$B$25 | I9: =G9-H9 | J9: =MAX(0,I9)*Supuestos!$B$15 | K9: =I9-J9 | L9: =L8+K9 | M9: =IF(L9>=0,A9,"")
A10: 6 | B10: 65 | C10: =ROUND(B10*$F$2,0) | D10: =C10*Supuestos!$B$10 | E10: =C10*Supuestos!$G$10 | F10: =C10*Supuestos!$H$10 | G10: =E10-F10 | H10: =Supuestos!$B$25 | I10: =G10-H10 | J10: =MAX(0,I10)*Supuestos!$B$15 | K10: =I10-J10 | L10: =L9+K10 | M10: =IF(L10>=0,A10,"")
A11: 7 | B11: 75 | C11: =ROUND(B11*$F$2,0) | D11: =C11*Supuestos!$B$10 | E11: =C11*Supuestos!$G$10 | F11: =C11*Supuestos!$H$10 | G11: =E11-F11 | H11: =Supuestos!$B$25 | I11: =G11-H11 | J11: =MAX(0,I11)*Supuestos!$B$15 | K11: =I11-J11 | L11: =L10+K11 | M11: =IF(L11>=0,A11,"")
A12: 8 | B12: 85 | C12: =ROUND(B12*$F$2,0) | D12: =C12*Supuestos!$B$10 | E12: =C12*Supuestos!$G$10 | F12: =C12*Supuestos!$H$10 | G12: =E12-F12 | H12: =Supuestos!$B$25 | I12: =G12-H12 | J12: =MAX(0,I12)*Supuestos!$B$15 | K12: =I12-J12 | L12: =L11+K12 | M12: =IF(L12>=0,A12,"")
A13: 9 | B13: 95 | C13: =ROUND(B13*$F$2,0) | D13: =C13*Supuestos!$B$10 | E13: =C13*Supuestos!$G$10 | F13: =C13*Supuestos!$H$10 | G13: =E13-F13 | H13: =Supuestos!$B$25 | I13: =G13-H13 | J13: =MAX(0,I13)*Supuestos!$B$15 | K13: =I13-J13 | L13: =L12+K13 | M13: =IF(L13>=0,A13,"")
A14: 10 | B14: 105 | C14: =ROUND(B14*$F$2,0) | D14: =C14*Supuestos!$B$10 | E14: =C14*Supuestos!$G$10 | F14: =C14*Supuestos!$H$10 | G14: =E14-F14 | H14: =Supuestos!$B$25 | I14: =G14-H14 | J14: =MAX(0,I14)*Supuestos!$B$15 | K14: =I14-J14 | L14: =L13+K14 | M14: =IF(L14>=0,A14,"")
A15: 11 | B15: 115 | C15: =ROUND(B15*$F$2,0) | D15: =C15*Supuestos!$B$10 | E15: =C15*Supuestos!$G$10 | F15: =C15*Supuestos!$H$10 | G15: =E15-F15 | H15: =Supuestos!$B$25 | I15: =G15-H15 | J15: =MAX(0,I15)*Supuestos!$B$15 | K15: =I15-J15 | L15: =L14+K15 | M15: =IF(L15>=0,A15,"")
A16: 12 | B16: 125 | C16: =ROUND(B16*$F$2,0) | D16: =C16*Supuestos!$B$10 | E16: =C16*Supuestos!$G$10 | F16: =C16*Supuestos!$H$10 | G16: =E16-F16 | H16: =Supuestos!$B$25 | I16: =G16-H16 | J16: =MAX(0,I16)*Supuestos!$B$15 | K16: =I16-J16 | L16: =L15+K16 | M16: =IF(L16>=0,A16,"")
A17: Total año 1 | B17: =SUM(B5:B16) | C17: =SUM(C5:C16) | D17: =SUM(D5:D16) | E17: =SUM(E5:E16) | F17: =SUM(F5:F16) | G17: =SUM(G5:G16) | H17: =SUM(H5:H16) | I17: =SUM(I5:I16) | ... K17: =SUM(K5:K16)
A19: Mes en que recuperas la inversión | C19: =IF(COUNT(M5:M16)=0,"Más de 12 meses",MIN(M5:M16))
A20: Utilidad neta promedio de los últimos 3 meses | C20: =AVERAGE(K14:K16)
A22: La utilidad neta es lo que queda para ti (y luego para tus padres). Al inicio tú haces de técnico; el costo de mano de obra ya está incluido, así que si tú haces el servicio, ese pago también es tuyo.
A23: Con más de ~70 servicios al mes necesitas un segundo equipo; su pago ya está en la mano de obra por servicio.
